gluer/Factory.py
gluer/Gluer.py
gluer/Registration.py
gluer/__init__.py
gluer/exceptions.py
gluer/typing_helpers.py
gluer-0.0.1.dist-info/METADATA
gluer-0.0.1.dist-info/RECORD
gluer-0.0.1.dist-info/WHEEL
gluer-0.0.1.dist-info/top_level.txt
