Metadata-Version: 2.1
Name: gluer
Version: 0.0.1
Summary: Dependency injection for python
Home-page: UNKNOWN
Author: Kamil Maciejko
Author-email: maciejkokamil@gmail.com
License: UNKNOWN
Platform: UNKNOWN
Requires-Python: >=3.6.0
